async_storages/__init__.py
async_storages/_version.py
async_storages/base.py
async_storages/integrations/__init__.py
async_storages/integrations/sqlalchemy.py
async_storages/py.typed
async_storages/s3.py
async_storages/utils.py
fastapi_async_storages-0.1.3.dist-info/WHEEL
fastapi_async_storages-0.1.3.dist-info/METADATA
fastapi_async_storages-0.1.3.dist-info/RECORD
