Metadata-Version: 2.3
Name: fastapi-async-storages
Version: 0.1.3
Summary: A powerful, extensible, and async-ready cloud object storage backend for FastAPI.
Keywords: fastapi,async,storage,cloud,s3,object-storage,backend
Author: stabldev
Author-email: stabldev <thestabldev@gmail.com>
License: MIT
Classifier: Development Status :: 4 - Beta
Classifier: Environment :: Web Environment
Classifier: Framework :: FastAPI
Classifier: Intended Audience :: Developers
Classifier: License :: OSI Approved :: MIT License
Classifier: Operating System :: OS Independent
Classifier: Programming Language :: Python :: 3
Classifier: Programming Language :: Python :: 3 :: Only
Classifier: Programming Language :: Python :: 3.12
Classifier: Programming Language :: Python :: 3.13
Classifier: Topic :: Internet :: WWW/HTTP :: Dynamic Content
Classifier: Topic :: Software Development :: Libraries :: Python Modules
Classifier: Topic :: Utilities
Classifier: Typing :: Typed
Requires-Dist: aioboto3>=15.4.0 ; extra == 'docs'
Requires-Dist: furo>=2025.9.25 ; extra == 'docs'
Requires-Dist: pillow>=12.0.0 ; extra == 'docs'
Requires-Dist: sphinx>=8.2.3 ; extra == 'docs'
Requires-Dist: sqlalchemy>=2.0.44 ; extra == 'docs'
Requires-Dist: aioboto3>=15.4.0 ; extra == 's3'
Requires-Python: >=3.12
Project-URL: Homepage, https://github.com/stabldev/fastapi-async-storages
Project-URL: Repository, https://github.com/stabldev/fastapi-async-storages
Project-URL: Documentation, https://fastapi-async-storages.readthedocs.io
Project-URL: Changelog, https://github.com/stabldev/fastapi-async-storages/releases
Provides-Extra: docs
Provides-Extra: s3
